django_visit_counter/__init__.py
django_visit_counter/apps.py
django_visit_counter/middleware.py
django_visit_counter/urls.py
django_visit_counter/views.py
django_visit_counter/templates/visit_counter/personalized.html
django_visit_counter-0.1.3.dist-info/METADATA
django_visit_counter-0.1.3.dist-info/WHEEL
django_visit_counter-0.1.3.dist-info/top_level.txt
django_visit_counter-0.1.3.dist-info/RECORD
