Metadata-Version: 2.4
Name: django_visit_counter
Version: 0.1.3
Summary: Application Django pour personnaliser le contenu selon le nombre de visites par session.
Author: Momo
Author-email: omomo9414@email.com
Classifier: Framework :: Django
Classifier: Programming Language :: Python :: 3
Classifier: Operating System :: OS Independent
Classifier: License :: OSI Approved :: MIT License
Requires-Python: >=3.6
Requires-Dist: Django>=3.2
Dynamic: author
Dynamic: author-email
Dynamic: classifier
Dynamic: description
Dynamic: description-content-type
Dynamic: requires-dist
Dynamic: requires-python
Dynamic: summary
